[
  {
    "expression": "ぴくりぴくり",
    "shortDefinitions": [
      "体や体の一部などが間をおきながら何度もひきつるように、ふるえ動くさま。"
    ],
    "extendedDefinition": "",
    "sentenceExamples": [
      "ぴくりぴくりと鼻を膨らませる"
    ]
  },
  {
    "expression": "ぞろり",
    "shortDefinitions": [
      "多くのものが一つながりに並んでいるさま。",
      "衣服をひきずるように、だらしない感じに着流しているさま。"
    ],
    "extendedDefinition": "",
    "sentenceExamples": [
      "ぞろりと店の前に行列ができる",
      "ズボンの裾をぞろりとひきずる"
    ]
  },
  {
    "expression": "ぞーっ",
    "shortDefinitions": [
      "寒さや恐ろしさで体が震えあがるような感じのするさま。"
    ],
    "extendedDefinition": "",
    "sentenceExamples": [
      "背筋がぞーっと凍る",
      "想像しただけでぞーっとする"
    ]
  },
  {
    "expression": "ざっぶ",
    "shortDefinitions": [
      "勢いよく水中に飛びこむ音。",
      "ものが勢いよく水中に投げこまれる音。",
      "刀などで、ものを勢いよく断ち切る音。また、そのさま。"
    ],
    "extendedDefinition": "「ざっぷ」は勢いよく水中に飛びこむ音。ものが勢いよく水中に投げこまれる音を表すのに用いられます。",
    "sentenceExamples": [
      "ざっぷと鯉が跳ねる",
      "グラスが水桶にざっぷと浸かる",
      "ざっぷと川に飛び込む"
    ]
  },
  {
    "expression": "いちゃこちゃ",
    "shortDefinitions": [
      "あれこれと文句を言い合う様子。",
      "あれやこれやと言い訳をするさま。",
      "男女の恋愛沙汰。"
    ],
    "extendedDefinition": "「いちゃこちゃ」は言い訳をしたり、文句を言い合う様子を表すのに用いられます。多くの場合、男女の恋愛沙汰に対して使われます。\nまた、「いちゃこく」などのような方言と入り混じった表現なので、必ずしも言い訳をする様子というニュアンスだけではありません。",
    "sentenceExamples": [
      "いちゃこちゃと文句を言わないで仕事しろ！",
      "いくら友人とはいえ、毎度いちゃこちゃに巻き込まれるのはごめんだ……",
      "いちゃこちゃしているうちはまだ望みがあるよ"
    ]
  },
  {
    "expression": "おたおた",
    "shortDefinitions": [
      "不意の出来事に驚いたり、相手に気おされたりして、うろたえるさま。",
      "思いがけない事態に、どう対処していいかすぐに判断がつかず、何もできないさま。"
    ],
    "extendedDefinition": "「おたおた」は思いがけない事態に、どう対処していいかすぐに判断がつかず、何もできないさまを表すのに用いられます。",
    "sentenceExamples": [
      "財布を落としておたおたとする",
      "おたおたしてないで、自信を持って動け",
      "憧れの人を目の前におたおたするしかなかった"
    ]
  },
  {
    "expression": "おじおじ",
    "shortDefinitions": [
      "遠慮して恐れるさま。",
      "恐れるさま。恐る恐る。",
      "怯えたように、自信なさげにためらいつつ物事を行うさま。"
    ],
    "extendedDefinition": "「おじおじ」は遠慮して恐れるさまや、怯えたように自信なさげにためらいつつ物事を行うさまを表すのに用いられます。",
    "sentenceExamples": [
      "おじおじと彼女のお父さんに会う",
      "いつも君はおじおじとしているね",
      "おじおじしていないで、行くときは行け！"
    ]
  },
  {
    "expression": "おぎゃーおぎゃー",
    "shortDefinitions": [
      "赤ちゃんの泣き声。"
    ],
    "extendedDefinition": "「おぎゃーおぎゃー」は赤ちゃんの元気な泣き声を表すのに用いられます。\n江戸時代から使われている言葉です。",
    "sentenceExamples": [
      "赤ちゃんがおぎゃーおぎゃーと泣く",
      "病院の待合室で赤ちゃんのおぎゃーおぎゃーと泣き声が聞こえる",
      "おぎゃーおぎゃーと生まれる"
    ]
  },
  {
    "expression": "おーおー",
    "shortDefinitions": [
      "人が泣き叫ぶ声。また、そのさま。",
      "わめき騒ぐときの声。また、そのさま。",
      "応援の掛け声。また、そのさま。"
    ],
    "extendedDefinition": "「おーおー」は人が泣き叫んだり、わめき騒ぐときの声を表すのに用いられます。\nまた、最近では驚きを表現するときや、人から何かを言われて反論するときなどにも使われます。\n「おーおー、どうした急に」「おーおー、オレが音痴だって言うのか」など。",
    "sentenceExamples": [
      "おーおーと泣く母親",
      "スタジアムが歓声でおーおーとざわめく",
      "毎晩、2時過ぎると隣の家からおーおーと泣き叫ぶ声が聞こえる"
    ]
  },
  {
    "expression": "えんえん",
    "shortDefinitions": [
      "声をあげて泣く声。また、そのさま。",
      "何かを訴えるような甘えた感じの泣き方。"
    ],
    "extendedDefinition": "「えんえん」は子どもなどが声をあげて泣く声を表すのに用いられます。これ見よがしに泣く感じで、泣きまねにも使われます。\n「えーんえーん」は「えんえん」より激しい泣き方を表します。",
    "sentenceExamples": [
      "彼氏に振られて、毎日えんえんと泣いているよ",
      "えんえんと泣きじゃくる子ども",
      "えんえんと泣いていたって、誰も助けてくれないぞ"
    ]
  },
  {
    "expression": "えへん",
    "shortDefinitions": [
      "せきばらいの声。",
      "せきこんだり、人の注意を促すさま。",
      "いばっているさま。"
    ],
    "extendedDefinition": "「えへん」は咳払いをする声やその様子を表すのに用いられます。自慢気に威張る様子そのもを表すこともあります。",
    "sentenceExamples": [
      "風邪気味でえへんと咳をする",
      "えへん。本日の講義は――",
      "いつもえへんと威張っている上司"
    ]
  },
  {
    "expression": "えへへ",
    "shortDefinitions": [
      "人にこびたり、卑屈そうに笑う声。また、そのさま。",
      "つくり笑いや照れ笑いの声。また。そのさま。"
    ],
    "extendedDefinition": "「えへへ」は心の内を隠して場を取り繕うような笑いを表すのに用いられます。\n心の底からおかしくて笑うのではなく、照れ笑いや何かを誤魔化す作り笑いなどを表すニュアンスです。",
    "sentenceExamples": [
      "頭を撫でられてえへへと笑う",
      "えへへじゃねーよ。笑って誤魔化すな！",
      "褒められて、思わずえへへと笑う"
    ]
  },
  {
    "expression": "えーん",
    "shortDefinitions": [
      "泣くときに発する声。",
      "人目をはばからず、幼稚な感じで泣くさま。"
    ],
    "extendedDefinition": "「えーん」は泣くときに発する声を表すのに用いられます。\n「えーんえん」「え～ん」などの派生系があります。",
    "sentenceExamples": [
      "買ったばかりの携帯を落としてしまった。えーん",
      "えーん。まだ遊びたいのに",
      "また、振られてしまった。えーん"
    ]
  },
  {
    "expression": "うんざり",
    "shortDefinitions": [
      "ものごとがじゅうぶんすぎて、いやになるさま。",
      "同じ状態が続いたり、何度も繰り返されたりしてあきてしまうさま。",
      "期待が外れてがっかりするさま。"
    ],
    "extendedDefinition": "「うんざり」は飽きてうるさくて煩わしく感じられる様子を表すの用いられます。\n江戸時代あたりから、驚きや恐れからくる嫌悪感を表すニュアンスが加わりました。",
    "sentenceExamples": [
      "また、ハズレかよ。うんざりだ",
      "うんざりとするくらいの仕事量",
      "毎日、決められたことの繰り返しでうんざりする"
    ]
  },
  {
    "expression": "うわーん",
    "shortDefinitions": [
      "子どもなどが、大声で泣く声。",
      "空間にこだまする音。"
    ],
    "extendedDefinition": "「うわーん」は子どもなどが大声で泣く声やそのさまを表すのに用いられます。\n「うわん」「うわーーーーん」「うわーんうわーん」などの派生系があります。",
    "sentenceExamples": [
      "僕のカードが無くなっちゃった、うわーん",
      "迷子の子どもがうわーんと泣く",
      "うわーんと泣きたいのはこっちのほうだよ"
    ]
  },
  {
    "expression": "うるるん",
    "shortDefinitions": [
      "目に涙がいっばいたまるさま。",
      "目が涙などで潤いやつやが強く感じるさま。"
    ],
    "extendedDefinition": "「うるるん」は目に涙がいっばいたまるさまを表すのに用いられます。\nちなみに「世界ウルルン滞在記」は「出会ウ、泊まル、見ル、体験（タイケン）」をとってまとめたものとされています。",
    "sentenceExamples": [
      "うるるん瞳でリフレッシュ",
      "チワワがうるるんとした瞳で見てくる",
      "映画を見て、目がうるるんとしている"
    ]
  },
  {
    "expression": "うるっ",
    "shortDefinitions": [
      "思わず涙がこぼれそうになるさま。",
      "涙で瞳が潤むさま。",
      "感動して涙が溢れてくるさま"
    ],
    "extendedDefinition": "「うるっ」は思わず涙がこぼれそうになるさまを表すのに用いられます。涙が流れてくる前の段階にたいして使われます。",
    "sentenceExamples": [
      "息子からのプレゼントにうるっとくる母",
      "うるっとはきたけど泣きはしないかな",
      "映画を見て、思わずうるっとくる"
    ]
  },
  {
    "expression": "うるうる",
    "shortDefinitions": [
      "水気があり余るさま。",
      "つやのあるさま。",
      "目が涙でいっぱいになるさま。"
    ],
    "extendedDefinition": "「うるうる」は感動して涙があふれそうになる様子を表すのに用いられます。現代では、水気のあるさまやつやのあるさまよりも涙目のニュアンスが強いです。\n鎌倉時代から使われていたと考えられている言葉です。",
    "sentenceExamples": [
      "感動してうるうるとくる",
      "驚きで声が出せず、あくあくと口が動く",
      "ぶどうの一粒一粒がうるうるとしている"
    ]
  },
  {
    "expression": "うまうま",
    "shortDefinitions": [
      "たくみな手順で事をしとげるさま。",
      "快く感じられるさま。",
      "おいしく感じられるさま。"
    ],
    "extendedDefinition": "「うまうま」はたくみな手順で事をしとげるさまや、食べ物が美味しく感じられるさまを表すのに用いられます。\n一部のネット用語では、人の失敗を嬉しがるさまとして使われることもあります。",
    "sentenceExamples": [
      "何だか、うまうまとはめられている気がする",
      "うまうまとご飯を食べる",
      "大量リストラとか、うまうま"
    ]
  },
  {
    "expression": "うほうほ",
    "shortDefinitions": [
      "満足しきって心が浮かれているさま。",
      "ゴリラの鳴き声。"
    ],
    "extendedDefinition": "「うほうほ」は満足しきって心が浮かれているさまを表すのに用いられます。ゴリラの鳴き声にも使われます。\n「うほほ」「うほっ」などの派生系があります。\n最近では男性が男性を好意を表すときに使われることもあります。",
    "sentenceExamples": [
      "お小遣いをもらってうほうほとする",
      "うほうほとゴリラが胸を叩く",
      "あら、いい男！　うほうほ！"
    ]
  },
  {
    "expression": "うふっ",
    "shortDefinitions": [
      "小声で短く笑う声。",
      "笑いをこらえながら軽く出す声。",
      "強く抱き締められたときの息の音。"
    ],
    "extendedDefinition": "「うふっ」は抑え気味の短い笑い声を表すのに用いられます。吹き出すような感じの含み笑い。主に女性の含み笑い。\n「うふふふふ」「うふふ」「うふふふー」などの派生系があります。",
    "sentenceExamples": [
      "うふっ。馬鹿な人",
      "アイドルが不敵にうふっと笑う",
      "うふふふふっふー"
    ]
  },
  {
    "expression": "うひょうひょ",
    "shortDefinitions": [
      "うれしくて小さな笑いをもらす声。また、そのさま。",
      "満足して心が浮かれて笑う声。また、そのさま。"
    ],
    "extendedDefinition": "「うひょひょ」はうれしくて小さな笑いをもらす声を表すのに用いられます。\n「うひょ」「うひょっ」「うひょひょひょひょ」などの派生系があります。",
    "sentenceExamples": [
      "うひょひょ！　冷蔵庫にプリンがあるぞ！",
      "今から飲み会？　うひょひょ、行く行く！",
      "今日は楽しみにしていたピクニックだ。うひょひょ"
    ]
  },
  {
    "expression": "うひひ",
    "shortDefinitions": [
      "何か企みをもって野卑に笑う声。また、そのさま。",
      "声を殺して嘲笑するさま。"
    ],
    "extendedDefinition": "「うひひ」は満足感から露骨な喜びを抑えつつもこみあげてくる笑い声を表すのに用いられます。\n「うひひひひひ」「うひひっ」「うひ」などの派生系があります。",
    "sentenceExamples": [
      "私だけ一つおまけしてもらちゃった。うひひ",
      "うひひひひ。これで世界は私のものだ",
      "ここに罠をしかければ、きっと。うひひ"
    ]
  },
  {
    "expression": "うはは",
    "shortDefinitions": [
      "大口をあけて笑う声。また、そのさま。",
      "明るく、無遠慮に大満足に笑うさま。"
    ],
    "extendedDefinition": "「うはは」は大口をあけて笑う声を表すのに用いられます\n「うはうは」のニュアンスと近いのはもともと「うはは」がもとになって「うはうは」になったと考えられているからです。\n「うはははははっ」などの派生系もあります。",
    "sentenceExamples": [
      "お気にリの服を着てうははと笑う",
      "うははっ。ついに手に入れたぞ",
      "誠にあっぱれな男よ！　あはははははっ！"
    ]
  },
  {
    "expression": "うはうは",
    "shortDefinitions": [
      "うれしくて笑いがこみあげ、おさえられないさま。",
      "喜ばしい出来事があり、思わず笑ってしまうさま。",
      "非常に喜んで高揚しているさま。十分に満足しているさま。"
    ],
    "extendedDefinition": "「うはうは」は予想以上に大きな満足に自己の品位を忘れるほど笑いがこみ上げてくる様子を表すのに用いられます。\n人から見ると嫌味ったらしかったり、品がなく感じられることがあります。",
    "sentenceExamples": [
      "宝くじが当たってうはうはだ",
      "仕事も上手いってるし、綺麗な嫁さんもいてうはうはだな",
      "去年までうはうはだったのに……"
    ]
  },
  {
    "expression": "うっとり",
    "shortDefinitions": [
      "美しいもの、好ましいものなどによる快感に身をゆだねているさま。",
      "意識を失うさま。"
    ],
    "extendedDefinition": "「うっとり」は美しいもの、好ましいものなどに心を奪われ我を忘れている様子を表すのに用いられます。\n本来は注意が不足している状態を表した言葉でしたが、時代の変化で現在のようなニュアンスに変化していきました。",
    "sentenceExamples": [
      "アイドルのパフォーマンスにうっとりする",
      "うっとりと恍惚の笑みを浮かべる",
      "彼氏の一挙手一投足にうっとりとする彼女"
    ]
  },
  {
    "expression": "うっしっし",
    "shortDefinitions": [
      "うまくやったとほくそえむさま。",
      "牛をシャレで言った言葉。"
    ],
    "extendedDefinition": "「うっしっし」はうまくやったとほくそえむ様子を表すのに用いられます。最近では、笑う様子だけでなく牛をシャレで言うさいにも使われます。",
    "sentenceExamples": [
      "うっしっしとほくそ笑む",
      "上手くいったぞ。うっしっし",
      "うっしっし、これであいつもお終いよ"
    ]
  },
  {
    "expression": "うっかり",
    "shortDefinitions": [
      "あまり深く考えずに、ものごとを行うさま。",
      "放心しているさま。",
      "美しいもの、快いものなどに心をひかれているさま。",
      "心をひかれて他に注意の向かないさま。",
      "気が抜けているさま。"
    ],
    "extendedDefinition": "「うっかり」は本来は行うべき注意を怠って、ものごとを行うさまを表すのに用いられます。\nうっかりは室町時代から使われていた言葉だと考えられています。\nまた、「うっかり」は心が完全に離れてしまっているようなニュアンスが強いです。",
    "sentenceExamples": [
      "うっかりものの八兵衛",
      "テレビゲームをしてたら、うっかりして待ち合わせ時間に遅れる",
      "うっかりしている間に自分の番が回ってくる"
    ]
  },
  {
    "expression": "うつうつ",
    "shortDefinitions": [
      "なかば眠り、なかばさめているさま。",
      "心の中に不安や心配があって思い沈むさま。(鬱鬱）",
      "草木がよく茂っているさま。"
    ],
    "extendedDefinition": "「うつうつ」はなかば眠り、なかば覚めているさま（夢うつつ）や鬱々としたさまを表すのに用いられます。\n最近では、鬱としての意味合いが強いです。",
    "sentenceExamples": [
      "ソファーでうつうつとする猫",
      "うつうつとした日々が続く",
      "うつうつした曲より、エレキサウンドのハイテンポな曲が聞きたい"
    ]
  },
  {
    "expression": "うだうだ",
    "shortDefinitions": [
      "際限もなく、あれこれと言い訳やぐちを言い続けるさま。",
      "怠惰に過ごすさま。",
      "無意味なことをしたり言ったりするさま。"
    ],
    "extendedDefinition": "「うだうだ」はどうでもいいことをや、つまらないことをとりとめなく言う様子や怠惰なさまを表すのに用いられます。\nうだうだはどうでもいいことを言ってる内容に対して使うニュアンスが強いです。",
    "sentenceExamples": [
      "うだうだ文句ばかり言っていないで、仕事しろ",
      "うだうだ言っていても仕方ない",
      "帰りたい。うだうだ仕事をするくらいなら……"
    ]
  },
  {
    "expression": "うずうず",
    "shortDefinitions": [
      "何かをしたくてたまらないさま。",
      "はれものなどの痛みを、にぶく感じ続けるさま。",
      "落ち着いていられない気持ちになるさま。",
      "虫などが気味わるくこまかく動き続けるさま。",
      "小さい声で不平を言う様子。"
    ],
    "extendedDefinition": "「うずうず」は何かをしたくてたまらなくて、落ち着かない様子や気持ちを表すのに用いられます。\n傷やはれものなどが鈍く痛む様子を表すのにも使われます。\n「うずうず」は痛みの様子や、やりたくてもできないはがゆい気持ちに対してのニュアンスが強いです。",
    "sentenceExamples": [
      "明日は試合だ。　体がうずうずしてくる",
      "猫にひっかかれた傷がうずうずする",
      "まだかな、まだかな。うずうず、うずうず"
    ]
  },
  {
    "expression": "うじうじ",
    "shortDefinitions": [
      "勇気がなかったり。具合のわるいことがあったりして、しなければならないと知りつつためらっているさま。",
      "絶えず小さく動いて落ち着きのないさま。",
      "小さい虫のはいまわるさま。"
    ],
    "extendedDefinition": "「うじうじ」は決断することができずに迷ったり、行動をためらう様子を表すのに用いられます。\n「うじうじ」は卑屈さや自信がないようなニュアンスがありますが、「うじうじ」は根底に迷いの気持ちが含まれています。",
    "sentenceExamples": [
      "うじうじしてないで、前を向けよ",
      "小さな虫がうじうじとしている",
      "うじうじしないで、すぐに決断を下す"
    ]
  },
  {
    "expression": "うしうし",
    "shortDefinitions": [
      "物事がうまくいって嬉しがるさま。",
      "結果に納得がいって喜ぶさま。"
    ],
    "extendedDefinition": "「うしうし」は物事がうまくいって嬉しがるさまを表すのに用いられます。言い切り系で「うっし」も同じようなニュアンスで使われます。\n「うっしし」と混ざり合っていやらしさを含む笑いとして使われることもあります。（しめしめ）",
    "sentenceExamples": [
      "狙ったガチャがでた！　うしうし！",
      "うしうし、今日は熱燗で一杯やるか",
      "うしうし！　元気が出てきた！"
    ]
  },
  {
    "expression": "うぎゃー",
    "shortDefinitions": [
      "驚いたときなどにあげる声。また、そのさま。",
      "赤ちゃんや子どもの泣き声。",
      "強い痛みを感じて叫ぶ声。また、そのさま。"
    ],
    "extendedDefinition": "「うぎゃー」は驚いたときなどにあげる声を表すのに用いられます。叫ぶニュアンスが強いです。\n予想外や想像以上の悪い結果に対して、悲鳴をあげるような声としても使われます。",
    "sentenceExamples": [
      "うぎゃー！　寝過ごした！",
      "そんな馬鹿な。こんなことになるなんてうぎゃー！",
      "うぎゃー！　超イケメン！"
    ]
  }
]